[
  {
    "id": "categorias",
    "name": "categorias",
    "type": "base",
    "system": false,
    "schema": [
      {
        "id": "nombre_field",
        "name": "nombre",
        "type": "text",
        "system": false,
        "required": true,
        "unique": true,
        "options": {
          "min": null,
          "max": null,
          "pattern": ""
        }
      },
      {
        "id": "activo_field",
        "name": "activo",
        "type": "bool",
        "system": false,
        "required": true,
        "unique": false,
        "options": {}
      },
      {
        "id": "fecha_alta_field",
        "name": "fecha_alta",
        "type": "date",
        "system": false,
        "required": true,
        "unique": false,
        "options": {
          "min": "",
          "max": ""
        }
      }
    ],
    "listRule": "",
    "viewRule": "",
    "createRule": "",
    "updateRule": "",
    "deleteRule": ""
  },
  {
    "id": "proveedores",
    "name": "proveedores",
    "type": "base",
    "system": false,
    "schema": [
      {
        "id": "nombre_field",
        "name": "nombre",
        "type": "text",
        "system": false,
        "required": true,
        "unique": true,
        "options": {
          "min": null,
          "max": null,
          "pattern": ""
        }
      },
      {
        "id": "activo_field",
        "name": "activo",
        "type": "bool",
        "system": false,
        "required": true,
        "unique": false,
        "options": {}
      },
      {
        "id": "fecha_alta_field",
        "name": "fecha_alta",
        "type": "date",
        "system": false,
        "required": true,
        "unique": false,
        "options": {
          "min": "",
          "max": ""
        }
      }
    ],
    "listRule": "",
    "viewRule": "",
    "createRule": "",
    "updateRule": "",
    "deleteRule": ""
  },
  {
    "id": "productos",
    "name": "productos",
    "type": "base",
    "system": false,
    "schema": [
      {
        "id": "codigo_field",
        "name": "codigo",
        "type": "text",
        "system": false,
        "required": true,
        "unique": false,
        "options": {
          "min": null,
          "max": null,
          "pattern": ""
        }
      },
      {
        "id": "nombre_field",
        "name": "nombre",
        "type": "text",
        "system": false,
        "required": true,
        "unique": false,
        "options": {
          "min": null,
          "max": null,
          "pattern": ""
        }
      },
      {
        "id": "precio_field",
        "name": "precio",
        "type": "number",
        "system": false,
        "required": true,
        "unique": false,
        "options": {
          "min": null,
          "max": null
        }
      },
      {
        "id": "activo_field",
        "name": "activo",
        "type": "bool",
        "system": false,
        "required": true,
        "unique": false,
        "options": {}
      },
      {
        "id": "fecha_alta_field",
        "name": "fecha_alta",
        "type": "date",
        "system": false,
        "required": true,
        "unique": false,
        "options": {
          "min": "",
          "max": ""
        }
      },
      {
        "id": "categoria_field",
        "name": "categoria",
        "type": "relation",
        "system": false,
        "required": false,
        "unique": false,
        "options": {
          "collectionId": "categorias",
          "cascadeDelete": false,
          "minSelect": null,
          "maxSelect": 1,
          "displayFields": []
        }
      },
      {
        "id": "proveedor_field",
        "name": "proveedor",
        "type": "relation",
        "system": false,
        "required": false,
        "unique": false,
        "options": {
          "collectionId": "proveedores",
          "cascadeDelete": false,
          "minSelect": null,
          "maxSelect": 1,
          "displayFields": []
        }
      }
    ],
    "listRule": "",
    "viewRule": "",
    "createRule": "",
    "updateRule": "",
    "deleteRule": ""
  },
  {
    "id": "importaciones",
    "name": "importaciones",
    "type": "base",
    "system": false,
    "schema": [
      {
        "id": "fecha_field",
        "name": "fecha",
        "type": "date",
        "system": false,
        "required": true,
        "unique": false,
        "options": {
          "min": "",
          "max": ""
        }
      },
      {
        "id": "proveedor_field",
        "name": "proveedor",
        "type": "text",
        "system": false,
        "required": true,
        "unique": false,
        "options": {
          "min": null,
          "max": null,
          "pattern": ""
        }
      },
      {
        "id": "tipo_field",
        "name": "tipo",
        "type": "text",
        "system": false,
        "required": true,
        "unique": false,
        "options": {
          "min": null,
          "max": null,
          "pattern": ""
        }
      },
      {
        "id": "estado_field",
        "name": "estado",
        "type": "text",
        "system": false,
        "required": true,
        "unique": false,
        "options": {
          "min": null,
          "max": null,
          "pattern": ""
        }
      },
      {
        "id": "archivo_field",
        "name": "archivo",
        "type": "text",
        "system": false,
        "required": true,
        "unique": false,
        "options": {
          "min": null,
          "max": null,
          "pattern": ""
        }
      },
      {
        "id": "log_field",
        "name": "log",
        "type": "text",
        "system": false,
        "required": false,
        "unique": false,
        "options": {
          "min": null,
          "max": null,
          "pattern": ""
        }
      }
    ],
    "listRule": "",
    "viewRule": "",
    "createRule": "",
    "updateRule": "",
    "deleteRule": ""
  },
  {
    "id": "devoluciones",
    "name": "devoluciones",
    "type": "base",
    "system": false,
    "schema": [
      {
        "id": "fecha_field",
        "name": "fecha",
        "type": "date",
        "system": false,
        "required": true,
        "unique": false,
        "options": {
          "min": "",
          "max": ""
        }
      },
      {
        "id": "motivo_field",
        "name": "motivo",
        "type": "text",
        "system": false,
        "required": true,
        "unique": false,
        "options": {
          "min": null,
          "max": null,
          "pattern": ""
        }
      },
      {
        "id": "cantidad_field",
        "name": "cantidad",
        "type": "number",
        "system": false,
        "required": true,
        "unique": false,
        "options": {
          "min": null,
          "max": null
        }
      },
      {
        "id": "producto_field",
        "name": "producto",
        "type": "relation",
        "system": false,
        "required": false,
        "unique": false,
        "options": {
          "collectionId": "productos",
          "cascadeDelete": false,
          "minSelect": null,
          "maxSelect": 1,
          "displayFields": []
        }
      }
    ],
    "listRule": "",
    "viewRule": "",
    "createRule": "",
    "updateRule": "",
    "deleteRule": ""
  }
]
